LucidDynamodb/__init__.py
LucidDynamodb/exceptions.py
LucidDynamodb/operations.py
LucidDynamodb/utils.py
tests/__init__.py
tests/test_crud.py
LucidDynamodb-1.0.128.dist-info/LICENSE
LucidDynamodb-1.0.128.dist-info/METADATA
LucidDynamodb-1.0.128.dist-info/WHEEL
LucidDynamodb-1.0.128.dist-info/top_level.txt
LucidDynamodb-1.0.128.dist-info/RECORD
