Metadata-Version: 2.1
Name: LucidDynamodb
Version: 1.0.128
Summary: A simple Python wrapper to AWS Dynamodb
Home-page: https://github.com/dineshsonachalam/Lucid-Dynamodb
Author: Dinesh Sonachalam
Author-email: dineshsonachalam@gmail.com
License: MIT
Keywords: python dynamodb amazon
Platform: UNKNOWN
Classifier: Programming Language :: Python :: 3
Classifier: License :: OSI Approved :: MIT License
Classifier: Operating System :: OS Independent
Requires-Python: >=3.1
Requires-Dist: boto3 (>=1.17.78)
Requires-Dist: botocore (>=1.20.78)
